taromaru/__init__.py
Taromaru-0.0.3.dist-info/LICENSE
Taromaru-0.0.3.dist-info/METADATA
Taromaru-0.0.3.dist-info/WHEEL
Taromaru-0.0.3.dist-info/top_level.txt
Taromaru-0.0.3.dist-info/RECORD
