Metadata-Version: 2.1
Name: Taromaru
Version: 0.0.3
Summary: A package to use my API with Python!
Home-page: https://github.com/Taromaruu/taromaru
Author: Doggotaco
Author-email: no@no.no
License: UNKNOWN
Platform: UNKNOWN
Classifier: Programming Language :: Python :: 3
Classifier: License :: OSI Approved :: MIT License
Classifier: Operating System :: OS Independent
Requires-Python: >=3.6
Requires-Dist: requests
Requires-Dist: aiohttp
